{
  "type": "minecraft:crafting_shaped",
  "category": "misc",
  "key": {
    "R": {
      "tag": "c:redstone_dusts"
    },
    "s": {
      "tag": "c:steel_ingots"
    },
    "i": {
      "tag": "c:iron_gears"
    },
    "S": {
      "tag": "c:silicon_blocks"
    },
    "B": {
      "item": "energizedpower:basic_circuit"
    },
    "H": {
      "item": "energizedpower:hardened_machine_frame"
    }
  },
  "pattern": [
    "iRi",
    "BHB",
    "SsS"
  ],
  "result": {
    "item": "energizedpower:assembling_machine"
  }
}