{
  "type": "minecraft:crafting_shaped",
  "category": "misc",
  "key": {
    "R": {
      "tag": "forge:dusts/redstone"
    },
    "s": {
      "tag": "forge:ingots/steel"
    },
    "i": {
      "tag": "forge:gears/iron"
    },
    "S": {
      "tag": "forge:storage_blocks/silicon"
    },
    "B": {
      "item": "energizedpower:basic_circuit"
    },
    "H": {
      "item": "energizedpower:hardened_machine_frame"
    }
  },
  "pattern": [
    "iRi",
    "BHB",
    "SsS"
  ],
  "result": {
    "item": "energizedpower:assembling_machine"
  }
}