{
  "type": "energizedpower:pulverizer",
  "ingredient": "#c:storage_blocks/raw_tin",
  "result": {
    "percentages": [
      1.0,
      1.0,
      1.0,
      1.0,
      1.0,
      1.0,
      1.0,
      1.0,
      1.0,
      0.5,
      0.5,
      0.25
    ],
    "percentagesAdvanced": [
      1.0,
      1.0,
      1.0,
      1.0,
      1.0,
      1.0,
      1.0,
      1.0,
      1.0,
      0.75,
      0.5,
      0.25,
      0.25
    ],
    "result": {
      "count": 1,
      "id": "energizedpower:tin_dust"
    }
  }
}